cropmirror/calc_geotiff_area/__init__.py
cropmirror/calc_geotiff_area/src/analyze_geotiff_crs.py
cropmirror/example/__init__.py
cropmirror/example/eat/__init__.py
cropmirror/example/eat/apple.py
cropmirror/example/say.py
cropmirror/ndvi/__init__.py
cropmirror/ndvi/generatevalues/common.py
cropmirror/ndvi/generatevalues/fertilization.py
cropmirror/ndvi/generatevalues/irrigation.py
cropmirror/ndvi/generatevalues/seedling.py
cropmirror/ndvi/generatevalues/spraying.py
cropmirror/ndvi/growth/vigor_monitoring.py
cropmirror/ndvi/prescription/__init__.py
cropmirror/ndvi/prescription/common.py
cropmirror/ndvi/prescription/fertilization_prescription.py
cropmirror/ndvi/prescription/files.py
cropmirror/ndvi/prescription/irrigation_prescription.py
cropmirror/ndvi/prescription/spraying_prescription.py
cropmirror/ndvi/README.md
cropmirror/planet/__init__.py
cropmirror/planet/constants.py
cropmirror/planet/planet_preprocessor.py
cropmirror/planet/planetMeta/__init__.py
cropmirror/planet/planetMeta/order.py
cropmirror/planet/planetMeta/search.py
cropmirror/planet/README.md
cropmirror/planet/request/__init__.py
cropmirror/planet/request/requestOrder.py
cropmirror/planet/request/requestSearch.py
cropmirror/remote_sensing/__init__.py
cropmirror/remote_sensing/clustering.py
cropmirror/remote_sensing/constants.py
cropmirror/remote_sensing/idw.py
cropmirror/remote_sensing/indicators.py
cropmirror/remote_sensing/io.py
cropmirror/remote_sensing/masking.py
cropmirror/remote_sensing/pipeline.py
cropmirror/remote_sensing/processor.py
cropmirror/remote_sensing/README.md
cropmirror/remote_sensing/shapefile_processor.py
cropmirror/remote_sensing/visualization.py
cropmirror/rgb/ngrdi.py
cropmirror/utils/__init__.py
cropmirror/utils/geojson_format_conversion.py
cropmirror/utils/geotiff_toolkit/reclassify.py
cropmirror/utils/getcoordinates.py
cropmirror/utils/polygon.py
cropmirror/utils/qgis_crs_utils.py
cropmirror/utils/shp2geojson.py
cropmirror/utils/shp_toolkit/toolkit.py
cropmirror-0.0.11.dist-info/LICENSE
cropmirror-0.0.11.dist-info/METADATA
cropmirror-0.0.11.dist-info/WHEEL
cropmirror-0.0.11.dist-info/RECORD
