Metadata-Version: 2.3
Name: cropmirror
Version: 0.0.11
Summary: 云稷基础算法库
License: MIT
Author: Long.liu
Requires-Python: >=3.10,<4
Classifier: Programming Language :: Python :: 3
Classifier: Operating System :: OS Independent
Classifier: License :: OSI Approved :: MIT License
Requires-Dist: Pillow (>=10.0.0,<11.0.0)
Requires-Dist: fiona (>=1.10.1,<2.0.0)
Requires-Dist: gdal
Requires-Dist: geojson (>=3.2.0,<4.0.0)
Requires-Dist: geopandas (>=1.0.1,<2.0.0)
Requires-Dist: geopy (>=2.4.1,<3.0.0)
Requires-Dist: matplotlib (>=3.10.1,<4.0.0)
Requires-Dist: numpy (>=2.1.0)
Requires-Dist: opencv-python (>=4.11.0.86,<5.0.0.0)
Requires-Dist: pyproj (>=3.6.0,<4.0.0)
Requires-Dist: pyshp (>=2.3.0,<3.0.0)
Requires-Dist: rasterio (>=1.4.3,<2.0.0)
Requires-Dist: rasterstats (>=0.20.0,<0.21.0)
Requires-Dist: requests (>=2.31.0,<3.0.0)
Requires-Dist: scikit-image (>=0.24.0,<1.0.0)
Requires-Dist: scikit-learn (>=1.7.0,<2.0.0)
Requires-Dist: scipy (>=1.15.2,<2.0.0)
Requires-Dist: shapely (>=2.0.0,<3.0.0)
Project-URL: Bug Tracker, https://github.com/cropmirror/cropmirror-utils/issues
Project-URL: Repository, https://github.com/cropmirror/cropmirror-utils
